{"flow":{"onboarding":{"$contentActions":[{"input":{"bypass":false,"$cardContent":{"document":{"id":"d9407639-39b1-43fa-8012-a005e25a7daf","type":"text/plain","content":"Entrada do usuário"},"editable":false,"deletable":false,"position":"right","editing":false},"$invalid":false},"$invalid":false}],"$conditionOutputs":[{"stateId":"welcome","conditions":[{"source":"input","comparison":"matches","values":[".*"]}],"$id":"16ebb874-6816-49ba-ab35-b4d18ea1ad7f","$connId":"con_3","$invalid":false}],"$enteringCustomActions":[],"$leavingCustomActions":[],"$inputSuggestions":[],"$defaultOutput":{"stateId":"fallback","$invalid":false},"isAiGenerated":false,"$tags":[],"id":"onboarding","root":true,"$title":"Início","$position":{"top":"120px","left":"644px"},"$invalidContentActions":false,"$invalidOutputs":false,"$invalidCustomActions":false,"$invalid":false},"fallback":{"$contentActions":[{"input":{"bypass":true,"$cardContent":{"document":{"id":"7a8fc673-b9aa-4f5b-88ad-5898103c4d52","type":"text/plain","content":"Entrada do usuário"},"editable":false,"deletable":true,"position":"right","editing":false},"$invalid":false},"$invalid":false}],"$conditionOutputs":[{"stateId":"error","conditions":[{"source":"input","comparison":"matches","values":[".*"]}],"$id":"5a401af7-cfce-40a2-b70c-ed31456c1f9b","$connId":"con_8","$invalid":false}],"$enteringCustomActions":[],"$leavingCustomActions":[],"$inputSuggestions":[],"$defaultOutput":{"stateId":"onboarding","$invalid":false},"isAiGenerated":false,"$tags":[],"id":"fallback","$title":"Exceções","$position":{"top":"362.5px","left":"140.75px"},"$invalidContentActions":false,"$invalidOutputs":false,"$invalidCustomActions":false,"$invalid":false},"welcome":{"$contentActions":[{"action":{"$id":"d6a2f812-7617-4def-ac76-1f02f37c9f19","$typeOfContent":"","type":"SendMessage","settings":{"id":"00000000-0000-0000-0000-000000000000","type":"application/vnd.lime.chatstate+json","content":{"state":"composing","interval":1000}},"$cardContent":{"document":{"id":"00000000-0000-0000-0000-000000000000","type":"application/vnd.lime.chatstate+json","content":{"state":"composing","interval":1000}},"editable":true,"deletable":true,"position":"left","editing":false}},"$invalid":false},{"action":{"$id":"f832cb5f-e265-4738-b6eb-34da64a17305","$typeOfContent":"","type":"SendMessage","settings":{"id":"00000000-0000-0000-0000-000000000001","type":"text/plain","content":"Hello, {{contact.name}}!","metadata":{}},"$cardContent":{"document":{"id":"00000000-0000-0000-0000-000000000001","type":"text/plain","content":"Hello, {{contact.name}}!"},"editable":true,"deletable":true,"position":"left","editing":false}},"$invalid":false},{"action":{"$id":"40e167a0-5b5c-44a2-9089-8df66d7b7140","$typeOfContent":"chat-state","type":"SendMessage","settings":{"id":"9f30cf54-5d05-4231-acb2-4442a291cadb","type":"application/vnd.lime.chatstate+json","content":{"state":"composing","interval":1000}},"$cardContent":{"document":{"id":"9f30cf54-5d05-4231-acb2-4442a291cadb","type":"application/vnd.lime.chatstate+json","content":{"state":"composing","interval":1000}},"editable":true,"deletable":true,"position":"left"}},"$invalid":false},{"action":{"$id":"227b3666-c851-4859-b601-d92099cc50d1","$typeOfContent":"text","type":"SendMessage","settings":{"id":"53b317fa-9387-4c19-bc8b-b040dfcea156","type":"text/plain","content":"This is a bot created for the RAG discipline (Large Language Models Applied to Retrieval-Augmented Generation) of UFPEL's PPGC.","metadata":{}},"$cardContent":{"document":{"id":"53b317fa-9387-4c19-bc8b-b040dfcea156","type":"text/plain","content":"This is a bot created for the RAG discipline (Large Language Models Applied to Retrieval-Augmented Generation) of UFPEL's PPGC."},"editable":true,"deletable":true,"position":"left"}},"$invalid":false},{"input":{"bypass":true,"$cardContent":{"document":{"id":"85fe6688-4076-43fa-bcaf-110f866303d8","type":"text/plain","content":"Entrada do usuário"},"editable":false,"deletable":true,"position":"right","editing":false},"$invalid":false},"$invalid":false}],"$conditionOutputs":[{"stateId":"a9d38dc8-1b38-403f-8a87-537dedcd5fb9","typeOfStateId":"state","$connId":"con_13","$id":"a89cbce8-1966-4766-a2a0-b9775b631cc4","conditions":[{"source":"context","comparison":"equals","values":["5419034633@telegram.gw.msging.net","247492973@telegram.gw.msging.net"],"variable":"contact.identity"}],"$invalid":false}],"$enteringCustomActions":[],"$leavingCustomActions":[],"$inputSuggestions":[],"$defaultOutput":{"stateId":"997c000b-b550-46e9-b838-2b6e7a4ae2f9","$invalid":false,"typeOfStateId":"state"},"isAiGenerated":false,"$tags":[],"id":"welcome","$title":"Boas vindas","$position":{"top":"239px","left":"645px"},"$invalidContentActions":false,"$invalidOutputs":false,"$invalidCustomActions":false,"$invalid":false},"error":{"$contentActions":[{"action":{"$id":"1aff04fb-f854-4013-b586-5df64376e19d","$typeOfContent":"","type":"SendMessage","settings":{"id":"00000000-0000-0000-0000-000000000002","type":"application/vnd.lime.chatstate+json","content":{"state":"composing","interval":1000}},"$cardContent":{"document":{"id":"00000000-0000-0000-0000-000000000002","type":"application/vnd.lime.chatstate+json","content":{"state":"composing","interval":1000}},"editable":true,"deletable":true,"position":"left","editing":false}},"$invalid":false},{"action":{"$id":"f95b5502-2115-4252-abf4-7fd4b72c2e70","$typeOfContent":"","type":"SendMessage","settings":{"id":"00000000-0000-0000-0000-000000000003","type":"text/plain","content":"Sorry, I couldn't understand!","metadata":{}},"$cardContent":{"document":{"id":"00000000-0000-0000-0000-000000000003","type":"text/plain","content":"Sorry, I couldn't understand!"},"editable":true,"deletable":true,"position":"left","editing":false}},"$invalid":false},{"input":{"bypass":true,"$cardContent":{"document":{"id":"d210fe5d-ef02-4ea3-a2c9-263806c25419","type":"text/plain","content":"Entrada do usuário"},"editable":false,"deletable":true,"position":"right","editing":false},"$invalid":false},"$invalid":false}],"$conditionOutputs":[],"$enteringCustomActions":[],"$leavingCustomActions":[],"$inputSuggestions":[],"$defaultOutput":{"stateId":"onboarding","$invalid":false},"isAiGenerated":false,"$tags":[],"id":"error","$title":"Erro padrão","$position":{"top":"469px","left":"148px"},"$invalidContentActions":false,"$invalidOutputs":false,"$invalidCustomActions":false,"$invalid":false},"807ff9b5-bfae-4f67-9731-413e9ac76fef":{"$contentActions":[{"input":{"bypass":false,"$cardContent":{"document":{"id":"99306eb1-5de1-494e-bcf4-dd42f2e77a1b","type":"text/plain","textContent":"Entrada do usuário","content":"Entrada do usuário"},"editable":false,"deletable":true,"position":"right","editing":false},"$invalid":false},"$invalid":false}],"$conditionOutputs":[],"$enteringCustomActions":[],"$leavingCustomActions":[],"$inputSuggestions":[],"$defaultOutput":{"stateId":"fallback","$invalid":false},"isAiGenerated":false,"$tags":[{"background":"#61D36F","label":"TrackEvent","id":"blip-tag-f41b7b00-b59c-d843-5725-0c9644dd2cf5","canChangeBackground":false},{"background":"#FFEC03","label":"User Input","id":"blip-tag-7a4c3a7b-1d71-2b95-081c-5d3b43693a4e","canChangeBackground":false},{"background":"#FF4A1E","label":"SetVariable","id":"blip-tag-eaff4915-810c-5b41-4956-40baba7665db","canChangeBackground":false},{"background":"#7762E3","label":"ProcessHttp","id":"blip-tag-c96ab8c6-3a29-dbba-b075-041e93e9621a","canChangeBackground":false},{"background":"#FF961E","label":"ExecuteScript","id":"blip-tag-26e3cc14-0c37-b5a3-2563-48e2c08b5aae","canChangeBackground":false},{"background":"#FF1E90","label":"MergeContact","id":"blip-tag-632926eb-875c-d7f5-d9b2-7a574d4ceca5","canChangeBackground":false},{"background":"#1EA1FF","label":"Redirect","id":"blip-tag-73251b2b-1fba-cb62-0245-847ef953653c","canChangeBackground":false}],"id":"807ff9b5-bfae-4f67-9731-413e9ac76fef","root":false,"$title":"TEMPLATE","$position":{"top":"119px","left":"354px"},"$invalidContentActions":false,"$invalidOutputs":false,"$invalidCustomActions":false,"$invalid":false},"a9d38dc8-1b38-403f-8a87-537dedcd5fb9":{"$contentActions":[{"input":{"bypass":true,"$cardContent":{"document":{"id":"649cc6f9-8920-4e47-9e5b-2e60ec547ee3","type":"text/plain","textContent":"Entrada do usuário","content":"Entrada do usuário"},"editable":false,"deletable":true,"position":"right","editing":false},"$invalid":false},"$invalid":false}],"$conditionOutputs":[],"$enteringCustomActions":[],"$leavingCustomActions":[],"$inputSuggestions":[],"$defaultOutput":{"stateId":"92cf000d-b61d-4a78-bd4a-dc70b43a3294","$invalid":false,"typeOfStateId":"state"},"isAiGenerated":false,"$tags":[],"id":"a9d38dc8-1b38-403f-8a87-537dedcd5fb9","root":false,"$title":"Autorizado","$position":{"top":"431px","left":"645px"},"$invalidContentActions":false,"$invalidOutputs":false,"$invalidCustomActions":false,"$invalid":false},"997c000b-b550-46e9-b838-2b6e7a4ae2f9":{"$contentActions":[{"action":{"$id":"5d6cd4c6-89d5-414f-a4cd-3ca2e9d5710e","$typeOfContent":"chat-state","type":"SendMessage","settings":{"id":"abfbcb37-1534-4a21-9891-468f677107b7","type":"application/vnd.lime.chatstate+json","content":{"state":"composing","interval":1000}},"$cardContent":{"document":{"id":"abfbcb37-1534-4a21-9891-468f677107b7","type":"application/vnd.lime.chatstate+json","content":{"state":"composing","interval":1000}},"editable":true,"deletable":true,"position":"left"}},"$invalid":false},{"action":{"$id":"82de250e-d743-4a6f-8e86-14e1cecf1b7b","$typeOfContent":"text","type":"SendMessage","settings":{"id":"ad43632e-72b5-45c5-b07a-68fbae2ea628","type":"text/plain","content":"Sorry, but it seems you don’t have permission to talk to me ☹","metadata":{}},"$cardContent":{"document":{"id":"ad43632e-72b5-45c5-b07a-68fbae2ea628","type":"text/plain","content":"Sorry, but it seems you don’t have permission to talk to me ☹"},"editable":true,"deletable":true,"position":"left"}},"$invalid":false},{"input":{"bypass":false,"$cardContent":{"document":{"id":"649cc6f9-8920-4e47-9e5b-2e60ec547ee3","type":"text/plain","textContent":"Entrada do usuário","content":"Entrada do usuário"},"editable":false,"deletable":true,"position":"right","editing":false},"$invalid":false},"$invalid":false}],"$conditionOutputs":[],"$enteringCustomActions":[],"$leavingCustomActions":[],"$inputSuggestions":[],"$defaultOutput":{"stateId":"welcome","$invalid":false,"typeOfStateId":"state"},"isAiGenerated":false,"$tags":[],"id":"997c000b-b550-46e9-b838-2b6e7a4ae2f9","root":false,"$title":"Não Autorizado","$position":{"top":"333px","left":"647px"},"$invalidContentActions":false,"$invalidOutputs":false,"$invalidCustomActions":false,"$invalid":false},"92cf000d-b61d-4a78-bd4a-dc70b43a3294":{"$contentActions":[{"action":{"$id":"34d8b5cd-abb4-4c99-a992-50ae7479bc7a","$typeOfContent":"chat-state","type":"SendMessage","settings":{"id":"affa7581-34b4-46d3-8a41-5c5e71253d98","type":"application/vnd.lime.chatstate+json","content":{"state":"composing","interval":1000}},"$cardContent":{"document":{"id":"affa7581-34b4-46d3-8a41-5c5e71253d98","type":"application/vnd.lime.chatstate+json","content":{"state":"composing","interval":1000}},"editable":true,"deletable":true,"position":"left"}},"$invalid":false},{"action":{"$id":"e009fc52-ee6b-4958-b417-4f22a9257a79","$typeOfContent":"text","type":"SendMessage","settings":{"id":"b99dcf01-15e6-435b-8c4e-f6cc48728bcf","type":"text/plain","content":"What is your question?","metadata":{}},"$cardContent":{"document":{"id":"b99dcf01-15e6-435b-8c4e-f6cc48728bcf","type":"text/plain","content":"What is your question?"},"editable":true,"deletable":true,"position":"left"}},"$invalid":false},{"input":{"bypass":false,"$cardContent":{"document":{"id":"12b48ee4-abcb-449c-988f-238f5f18406d","type":"text/plain","textContent":"Entrada do usuário","content":"textRAG"},"editable":false,"deletable":true,"position":"right","editing":false},"$invalid":false,"variable":"textRAG"},"$invalid":false}],"$conditionOutputs":[],"$enteringCustomActions":[],"$leavingCustomActions":[],"$inputSuggestions":[],"$defaultOutput":{"stateId":"4ca064d0-65f2-4c9c-8bb3-0984b27c63cf","$invalid":false,"typeOfStateId":"state"},"isAiGenerated":false,"$tags":[],"id":"92cf000d-b61d-4a78-bd4a-dc70b43a3294","root":false,"$title":"Pergunta duvida","$position":{"top":"528.5px","left":"649.75px"},"$invalidContentActions":false,"$invalidOutputs":false,"$invalidCustomActions":false,"$invalid":false},"4ca064d0-65f2-4c9c-8bb3-0984b27c63cf":{"$contentActions":[{"action":{"$id":"3fb9c057-d63a-4aec-b150-67e725a95480","$typeOfContent":"chat-state","type":"SendMessage","settings":{"id":"625a5b7f-ff11-4260-82a6-c39d7debdf37","type":"application/vnd.lime.chatstate+json","content":{"state":"composing","interval":1000}},"$cardContent":{"document":{"id":"625a5b7f-ff11-4260-82a6-c39d7debdf37","type":"application/vnd.lime.chatstate+json","content":{"state":"composing","interval":1000}},"editable":true,"deletable":true,"position":"left"}},"$invalid":false},{"action":{"$id":"d249052b-e0e8-4b3a-9191-385264177d67","$typeOfContent":"text","type":"SendMessage","settings":{"id":"2b51adec-96d9-442b-9dd6-23d5ff49c832","type":"text/plain","content":"Looking for answer🔎","metadata":{}},"$cardContent":{"document":{"id":"2b51adec-96d9-442b-9dd6-23d5ff49c832","type":"text/plain","content":"Looking for answer🔎"},"editable":true,"deletable":true,"position":"left"}},"$invalid":false},{"input":{"bypass":true,"$cardContent":{"document":{"id":"5bcb1693-c402-424c-96f2-b9e4d43ac975","type":"text/plain","textContent":"Entrada do usuário","content":"Entrada do usuário"},"editable":false,"deletable":true,"position":"right","editing":false},"$invalid":false},"$invalid":false}],"$conditionOutputs":[{"stateId":"031ec1f6-7c0e-4116-bb82-6b490fcc62c0","typeOfStateId":"state","$connId":"con_18","$id":"54c9c1c5-c860-4485-b9ef-4b2888e5e5dd","conditions":[{"source":"context","comparison":"equals","values":["200"],"variable":"answerStatus"},{"values":["false"],"source":"context","comparison":"notEquals","variable":"answerBody@second_validation"},{"values":["false"],"source":"context","comparison":"equals","variable":"answerBody@second_validation.acceptable"}],"$invalid":false},{"stateId":"15ad2c56-5dfd-4b38-bb8d-8aaa9c7dc7d8","typeOfStateId":"state","$connId":"con_23","$id":"9f3e8cd2-c074-4685-a492-2aa6d626e1ac","conditions":[{"source":"context","comparison":"equals","values":["200"],"variable":"answerStatus"},{"values":["false"],"source":"context","comparison":"notEquals","variable":"answerBody@second_validation"},{"values":["true"],"source":"context","comparison":"equals","variable":"answerBody@second_validation.acceptable"}],"$invalid":false},{"stateId":"031ec1f6-7c0e-4116-bb82-6b490fcc62c0","typeOfStateId":"state","$connId":"con_28","$id":"7fd156ec-4987-429c-9b3e-b1ddded4b0c9","conditions":[{"source":"context","comparison":"equals","values":["200"],"variable":"answerStatus"},{"values":["false"],"source":"context","variable":"answerBody@second_gemini_answer","comparison":"notEquals"}],"$invalid":false},{"stateId":"68602b66-32c8-4b0b-902f-86cc23c356a1","typeOfStateId":"state","$connId":"con_33","$id":"859f27c4-68c7-4185-b9f8-dac7bb20cc88","conditions":[{"source":"context","comparison":"equals","values":["200"],"variable":"answerStatus"},{"values":["false"],"source":"context","comparison":"notEquals","variable":"answerBody@validation"},{"values":["true"],"source":"context","comparison":"equals","variable":"answerBody@validation.acceptable"}],"$invalid":false},{"stateId":"031ec1f6-7c0e-4116-bb82-6b490fcc62c0","typeOfStateId":"state","$connId":"con_38","$id":"d5a816ff-f6dc-4351-911c-f72d128a9b20","conditions":[{"source":"context","comparison":"equals","values":["200"],"variable":"answerStatus"},{"values":["false"],"source":"context","comparison":"equals","variable":"answerBody@validation"}],"$invalid":false}],"$enteringCustomActions":[],"$leavingCustomActions":[{"$id":"48bb5766-fcf2-452e-a159-f9c73750d02a","$typeOfContent":"","type":"ProcessHttp","$title":"GET /answer","$invalid":false,"settings":{"headers":{},"method":"GET","uri":"{{config.api}}/answer?text={{textRAG}}","responseStatusVariable":"answerStatus","responseBodyVariable":"answerBody"},"conditions":[]},{"$id":"ef9440cf-4f8e-4810-be2e-83a87fab45f7","$typeOfContent":"","type":"TrackEvent","$title":"Busca duvida","$invalid":false,"settings":{"extras":{},"category":"Busca duvida","action":"{{answerBody}}"},"conditions":[{"values":["200"],"source":"context","comparison":"equals","variable":"answerStatus"}]}],"$inputSuggestions":[],"$defaultOutput":{"stateId":"155ed963-80e2-49ee-a8cf-ef25ad8c65cf","$invalid":false,"typeOfStateId":"state"},"isAiGenerated":false,"$tags":[{"background":"#7762E3","label":"ProcessHttp","id":"blip-tag-c96ab8c6-3a29-dbba-b075-041e93e9621a","canChangeBackground":false},{"background":"#61D36F","label":"TrackEvent","id":"blip-tag-f41b7b00-b59c-d843-5725-0c9644dd2cf5","canChangeBackground":false}],"id":"4ca064d0-65f2-4c9c-8bb3-0984b27c63cf","root":false,"$title":"Busca duvida","$position":{"top":"231px","left":"887px"},"$invalidContentActions":false,"$invalidOutputs":false,"$invalidCustomActions":false,"$invalid":false},"155ed963-80e2-49ee-a8cf-ef25ad8c65cf":{"$contentActions":[{"action":{"$id":"a380e460-9d6f-482e-86b7-8adc5f169925","$typeOfContent":"chat-state","type":"SendMessage","settings":{"id":"3bcabe5d-fa9b-4224-82e6-32f01da3400e","type":"application/vnd.lime.chatstate+json","content":{"state":"composing","interval":1000}},"$cardContent":{"document":{"id":"3bcabe5d-fa9b-4224-82e6-32f01da3400e","type":"application/vnd.lime.chatstate+json","content":{"state":"composing","interval":1000}},"editable":true,"deletable":true,"position":"left"}},"$invalid":false},{"action":{"$id":"fbc06ebf-e117-4115-aebc-b6c4093a0e7e","$typeOfContent":"text","type":"SendMessage","settings":{"id":"63a0c78e-dd86-4455-bf65-3dfefae04983","type":"text/plain","content":"Sorry, we're experiencing system issues 🤡","metadata":{}},"$cardContent":{"document":{"id":"63a0c78e-dd86-4455-bf65-3dfefae04983","type":"text/plain","content":"Sorry, we're experiencing system issues 🤡"},"editable":true,"deletable":true,"position":"left"}},"$invalid":false},{"input":{"bypass":true,"$cardContent":{"document":{"id":"090a9479-df47-4a79-855d-cb28bacb0ec0","type":"text/plain","textContent":"Entrada do usuário","content":"Entrada do usuário"},"editable":false,"deletable":true,"position":"right","editing":false},"$invalid":false},"$invalid":false}],"$conditionOutputs":[],"$enteringCustomActions":[],"$leavingCustomActions":[],"$inputSuggestions":[],"$defaultOutput":{"stateId":"welcome","$invalid":false,"typeOfStateId":"state"},"isAiGenerated":false,"$tags":[],"id":"155ed963-80e2-49ee-a8cf-ef25ad8c65cf","root":false,"$title":"Erro de API","$position":{"top":"574px","left":"144px"},"$invalidContentActions":false,"$invalidOutputs":false,"$invalidCustomActions":false,"$invalid":false},"68602b66-32c8-4b0b-902f-86cc23c356a1":{"$contentActions":[{"action":{"$id":"27cf78d8-458b-4f3c-b489-23b6800390f7","$typeOfContent":"chat-state","type":"SendMessage","settings":{"id":"d62da380-fcc2-405d-9de1-5c9bed52b061","type":"application/vnd.lime.chatstate+json","content":{"state":"composing","interval":1000}},"$cardContent":{"document":{"id":"d62da380-fcc2-405d-9de1-5c9bed52b061","type":"application/vnd.lime.chatstate+json","content":{"state":"composing","interval":1000}},"editable":true,"deletable":true,"position":"left"}},"$invalid":false},{"action":{"$id":"a714e417-f1d0-4686-964f-0a98adc171db","$typeOfContent":"text","type":"SendMessage","settings":{"id":"620c757f-a7d9-46be-8564-480a8d6acc13","type":"text/plain","content":"The answer is:\n{{answerBody@gemini_answer.answer}}","metadata":{}},"$cardContent":{"document":{"id":"620c757f-a7d9-46be-8564-480a8d6acc13","type":"text/plain","content":"The answer is:\n{{answerBody@gemini_answer.answer}}"},"editable":true,"deletable":true,"position":"left"}},"$invalid":false},{"input":{"bypass":true,"$cardContent":{"document":{"id":"f13077d1-ef1d-4035-828b-af0f7331a39e","type":"text/plain","textContent":"Entrada do usuário","content":"Entrada do usuário"},"editable":false,"deletable":true,"position":"right","editing":false},"$invalid":false},"$invalid":false}],"$conditionOutputs":[],"$enteringCustomActions":[],"$leavingCustomActions":[],"$inputSuggestions":[],"$defaultOutput":{"stateId":"bf284791-6132-450e-8c16-f197528fa953","$invalid":false,"typeOfStateId":"state"},"isAiGenerated":false,"$tags":[],"id":"68602b66-32c8-4b0b-902f-86cc23c356a1","root":false,"$title":"Exibe resposta","$position":{"top":"239.111px","left":"1125px"},"$invalidContentActions":false,"$invalidOutputs":false,"$invalidCustomActions":false,"$invalid":false},"bf284791-6132-450e-8c16-f197528fa953":{"$contentActions":[{"action":{"$id":"1f08f5c8-2f5f-4e6f-9e50-98f31ab6598c","$typeOfContent":"chat-state","type":"SendMessage","settings":{"id":"d38cde6b-a0f1-4f4d-9c6d-09d55f3466dc","type":"application/vnd.lime.chatstate+json","content":{"state":"composing","interval":1000}},"$cardContent":{"document":{"id":"d38cde6b-a0f1-4f4d-9c6d-09d55f3466dc","type":"application/vnd.lime.chatstate+json","content":{"state":"composing","interval":1000}},"editable":true,"deletable":true,"position":"left"}},"$invalid":false},{"action":{"$id":"9de3d689-479a-4f73-9a76-05071e73fead","$typeOfContent":"select-immediate","type":"SendMessage","settings":{"id":"7af5e32e-771c-4b4b-87c7-e9320c71b84b","type":"application/vnd.lime.select+json","content":{"text":"Was this question helpful?","scope":"immediate","options":[{"text":"Yes","previewText":"Yes","value":null,"index":0,"type":null},{"text":"No","previewText":"No","value":null,"index":1,"type":null}],"quikReply":false},"metadata":{}},"$cardContent":{"document":{"id":"7af5e32e-771c-4b4b-87c7-e9320c71b84b","type":"application/vnd.lime.select+json","content":{"text":"Was this question helpful?","scope":"immediate","options":[{"text":"Yes","previewText":"Yes","value":null,"index":0,"type":null},{"text":"No","previewText":"No","value":null,"index":1,"type":null}],"quikReply":false}},"editable":true,"deletable":true,"position":"left"}},"$invalid":false},{"input":{"bypass":false,"$cardContent":{"document":{"id":"e8d62bd6-7a79-4a8a-8d23-42251e4577c5","type":"text/plain","textContent":"Entrada do usuário","content":"Entrada do usuário"},"editable":false,"deletable":true,"position":"right","editing":false},"$invalid":false},"$invalid":false}],"$conditionOutputs":[{"stateId":"16a84406-6679-4bff-8f0c-15e7220e35c0","typeOfStateId":"state","$connId":"con_43","$contentId":"9de3d689-479a-4f73-9a76-05071e73fead","$id":"f6ee1fe5-3c95-4451-9e67-b72cea2ac058","conditions":[{"source":"input","comparison":"equals","values":["Yes"]}],"$invalid":false},{"stateId":"1ae8c38d-1a6b-44fd-9611-ad7a1f127023","typeOfStateId":"state","$connId":"con_48","$contentId":"9de3d689-479a-4f73-9a76-05071e73fead","$id":"62edd453-9504-4235-aef2-aa2e8b9aa2c2","conditions":[{"source":"input","comparison":"equals","values":["No"]}],"$invalid":false}],"$enteringCustomActions":[],"$leavingCustomActions":[],"$inputSuggestions":["Yes","No"],"$defaultOutput":{"stateId":"fallback","$invalid":false},"isAiGenerated":false,"$tags":[],"id":"bf284791-6132-450e-8c16-f197528fa953","root":false,"$title":"Pergunta utilidade resposta","$position":{"top":"233px","left":"1348px"},"$invalidContentActions":false,"$invalidOutputs":false,"$invalidCustomActions":false,"$invalid":false},"16a84406-6679-4bff-8f0c-15e7220e35c0":{"$contentActions":[{"action":{"$id":"a17c50bc-e4d8-4696-ae35-b20f4fe458b2","$typeOfContent":"chat-state","type":"SendMessage","settings":{"id":"b0f87bee-6296-47b3-9722-6beae64d89cd","type":"application/vnd.lime.chatstate+json","content":{"state":"composing","interval":1000}},"$cardContent":{"document":{"id":"b0f87bee-6296-47b3-9722-6beae64d89cd","type":"application/vnd.lime.chatstate+json","content":{"state":"composing","interval":1000}},"editable":true,"deletable":true,"position":"left"}},"$invalid":false},{"action":{"$id":"d48e2f6d-44a7-4f87-92d0-cb6eb61e11da","$typeOfContent":"text","type":"SendMessage","settings":{"id":"7c50fa9e-643a-4ddf-a82a-c282cc2c19c7","type":"text/plain","content":"Cool! It's always great when we can help 😀","metadata":{}},"$cardContent":{"document":{"id":"7c50fa9e-643a-4ddf-a82a-c282cc2c19c7","type":"text/plain","content":"Cool! It's always great when we can help 😀"},"editable":true,"deletable":true,"position":"left"}},"$invalid":false},{"input":{"bypass":true,"$cardContent":{"document":{"id":"22f51684-1c73-4e53-bdd8-81216de6b60f","type":"text/plain","textContent":"Entrada do usuário","content":"Entrada do usuário"},"editable":false,"deletable":true,"position":"right","editing":false},"$invalid":false},"$invalid":false}],"$conditionOutputs":[],"$enteringCustomActions":[{"$id":"bac2e92d-4d96-4188-a1e0-f44ab7d0b051","$typeOfContent":"","type":"TrackEvent","$title":"Utilidade resposta","$invalid":false,"settings":{"extras":{},"category":"Utilidade resposta","action":"Util"},"conditions":[]},{"$id":"c1c91a17-39f8-419a-acb6-6a5de24b2624","$typeOfContent":"","type":"TrackEvent","$title":"Resposta util","$invalid":false,"settings":{"extras":{},"category":"Resposta util","action":"{{textRAG}} - {{answerBody}}"},"conditions":[]}],"$leavingCustomActions":[],"$inputSuggestions":[],"$defaultOutput":{"stateId":"welcome","$invalid":false,"typeOfStateId":"state"},"isAiGenerated":false,"$tags":[{"background":"#61D36F","label":"TrackEvent","id":"blip-tag-f41b7b00-b59c-d843-5725-0c9644dd2cf5","canChangeBackground":false}],"id":"16a84406-6679-4bff-8f0c-15e7220e35c0","root":false,"$title":"Resposta util","$position":{"top":"357.333px","left":"1345.89px"},"$invalidContentActions":false,"$invalidOutputs":false,"$invalidCustomActions":false,"$invalid":false},"1ae8c38d-1a6b-44fd-9611-ad7a1f127023":{"$contentActions":[{"action":{"$id":"4f97b73d-40fa-4475-8b2b-b8dd27b1190e","$typeOfContent":"chat-state","type":"SendMessage","settings":{"id":"bf89ad39-8c30-45b3-83f4-953fad52a12c","type":"application/vnd.lime.chatstate+json","content":{"state":"composing","interval":1000}},"$cardContent":{"document":{"id":"bf89ad39-8c30-45b3-83f4-953fad52a12c","type":"application/vnd.lime.chatstate+json","content":{"state":"composing","interval":1000}},"editable":true,"deletable":true,"position":"left"}},"$invalid":false},{"action":{"$id":"521d742e-4d1c-4512-b86f-3675f533e934","$typeOfContent":"text","type":"SendMessage","settings":{"id":"7f697640-2672-431b-96c2-d9cbddc7181d","type":"text/plain","content":"Oh no! I feel upset when that happens 😞","metadata":{}},"$cardContent":{"document":{"id":"7f697640-2672-431b-96c2-d9cbddc7181d","type":"text/plain","content":"Oh no! I feel upset when that happens 😞"},"editable":true,"deletable":true,"position":"left"}},"$invalid":false},{"input":{"bypass":true,"$cardContent":{"document":{"id":"6f8a36f8-7dea-49a3-a511-3cc5b0c862fa","type":"text/plain","textContent":"Entrada do usuário","content":"Entrada do usuário"},"editable":false,"deletable":true,"position":"right","editing":false},"$invalid":false},"$invalid":false}],"$conditionOutputs":[],"$enteringCustomActions":[{"$id":"25452a40-5eff-4ebd-908d-c3c4a1f2d0d5","$typeOfContent":"","type":"TrackEvent","$title":"Utilidade resposta","$invalid":false,"settings":{"extras":{},"category":"Utilidade resposta","action":"Inutil"},"conditions":[]},{"$id":"6ecb9661-dd76-49a6-874e-f224f5d326a5","$typeOfContent":"","type":"TrackEvent","$title":"Resposta inutil","$invalid":false,"settings":{"extras":{},"category":"Resposta inutil","action":"{{textRAG}} - {{answerBody}}"},"conditions":[]}],"$leavingCustomActions":[],"$inputSuggestions":[],"$defaultOutput":{"stateId":"welcome","$invalid":false,"typeOfStateId":"state"},"isAiGenerated":false,"$tags":[{"background":"#61D36F","label":"TrackEvent","id":"blip-tag-f41b7b00-b59c-d843-5725-0c9644dd2cf5","canChangeBackground":false}],"id":"1ae8c38d-1a6b-44fd-9611-ad7a1f127023","root":false,"$title":"Resposta inutil","$position":{"top":"469px","left":"1347px"},"$invalidContentActions":false,"$invalidOutputs":false,"$invalidCustomActions":false,"$invalid":false},"031ec1f6-7c0e-4116-bb82-6b490fcc62c0":{"$contentActions":[{"action":{"$id":"8e6c7da1-a6d2-48d9-983c-59e4af8b6893","$typeOfContent":"chat-state","type":"SendMessage","settings":{"id":"c4cab71c-9041-459b-995c-df4baac05d42","type":"application/vnd.lime.chatstate+json","content":{"state":"composing","interval":1000}},"$cardContent":{"document":{"id":"c4cab71c-9041-459b-995c-df4baac05d42","type":"application/vnd.lime.chatstate+json","content":{"state":"composing","interval":1000}},"editable":true,"deletable":true,"position":"left"}},"$invalid":false},{"action":{"$id":"12ba5b86-7209-4db0-99ab-a557ea63684c","$typeOfContent":"text","type":"SendMessage","settings":{"id":"ff1a58ec-45eb-4011-95a4-ac48bb1dc237","type":"text/plain","content":"Sorry, but we couldn't find an answer to your question ☹","metadata":{}},"$cardContent":{"document":{"id":"ff1a58ec-45eb-4011-95a4-ac48bb1dc237","type":"text/plain","content":"Sorry, but we couldn't find an answer to your question ☹"},"editable":true,"deletable":true,"position":"left"}},"$invalid":false},{"input":{"bypass":true,"$cardContent":{"document":{"id":"ec629ed3-4409-4deb-bcc2-4fb42aa4b658","type":"text/plain","textContent":"Entrada do usuário","content":"Entrada do usuário"},"editable":false,"deletable":true,"position":"right","editing":false},"$invalid":false},"$invalid":false}],"$conditionOutputs":[],"$enteringCustomActions":[],"$leavingCustomActions":[],"$inputSuggestions":[],"$defaultOutput":{"stateId":"welcome","$invalid":false,"typeOfStateId":"state"},"isAiGenerated":false,"$tags":[],"id":"031ec1f6-7c0e-4116-bb82-6b490fcc62c0","root":false,"$title":"Não encontrou resposta","$position":{"top":"450px","left":"1125px"},"$invalidContentActions":false,"$invalidOutputs":false,"$invalidCustomActions":false,"$invalid":false},"15ad2c56-5dfd-4b38-bb8d-8aaa9c7dc7d8":{"$contentActions":[{"action":{"$id":"27cf78d8-458b-4f3c-b489-23b6800390f7","$typeOfContent":"chat-state","type":"SendMessage","settings":{"id":"d62da380-fcc2-405d-9de1-5c9bed52b061","type":"application/vnd.lime.chatstate+json","content":{"state":"composing","interval":1000}},"$cardContent":{"document":{"id":"d62da380-fcc2-405d-9de1-5c9bed52b061","type":"application/vnd.lime.chatstate+json","content":{"state":"composing","interval":1000}},"editable":true,"deletable":true,"position":"left"}},"$invalid":false},{"action":{"$id":"a714e417-f1d0-4686-964f-0a98adc171db","$typeOfContent":"text","type":"SendMessage","settings":{"id":"620c757f-a7d9-46be-8564-480a8d6acc13","type":"text/plain","content":"The another answer is:\n{{answerBody@second_gemini_answer.answer}}","metadata":{}},"$cardContent":{"document":{"id":"620c757f-a7d9-46be-8564-480a8d6acc13","type":"text/plain","content":"The another answer is:\n{{answerBody@second_gemini_answer.answer}}"},"editable":true,"deletable":true,"position":"left"}},"$invalid":false},{"input":{"bypass":true,"$cardContent":{"document":{"id":"f13077d1-ef1d-4035-828b-af0f7331a39e","type":"text/plain","textContent":"Entrada do usuário","content":"Entrada do usuário"},"editable":false,"deletable":true,"position":"right","editing":false},"$invalid":false},"$invalid":false}],"$conditionOutputs":[],"$enteringCustomActions":[],"$leavingCustomActions":[],"$inputSuggestions":[],"$defaultOutput":{"stateId":"bf284791-6132-450e-8c16-f197528fa953","$invalid":false,"typeOfStateId":"state"},"isAiGenerated":false,"$tags":[],"id":"15ad2c56-5dfd-4b38-bb8d-8aaa9c7dc7d8","root":false,"$title":"Exibe outra resposta","$position":{"top":"334px","left":"1127px"},"$invalidContentActions":false,"$invalidOutputs":false,"$invalidCustomActions":false,"$invalid":false}},"globalActions":{"$contentActions":[],"$conditionOutputs":[],"$enteringCustomActions":[],"$leavingCustomActions":[],"$inputSuggestions":[],"$defaultOutput":{"stateId":"fallback","$invalid":false},"isAiGenerated":false,"$tags":[],"id":"global-actions","$invalidContentActions":false,"$invalidOutputs":false,"$invalidCustomActions":false,"$invalid":false}}